jupytercor/__init__.py
jupytercor/cli.py
jupytercor/extract64/__init__.py
jupytercor/filters/pandoc-ldotcarreaux.py
jupytercor/filters/pandoc-minted.py
jupytercor/filters/panflute-breakline.py
jupytercor/filters/panflute-bullet.py
jupytercor/filters/panflute-headers.py
jupytercor/images/__init__.py
jupytercor/templates/cornouaille.latex
jupytercor/templates/eisvogel.latex
jupytercor/utils/__init__.py
jupytercor-0.2.6.dist-info/LICENSE
jupytercor-0.2.6.dist-info/METADATA
jupytercor-0.2.6.dist-info/WHEEL
jupytercor-0.2.6.dist-info/entry_points.txt
jupytercor-0.2.6.dist-info/RECORD
