Metadata-Version: 2.1
Name: jupytercor
Version: 0.2.6
Summary: permet de convertir les cellules markdown d'un notebook jupyter avec pandoc
Home-page: https://github.com/infocornouaille/jupytercor
License: MIT
Keywords: latex,jupyter,notebook
Author: David Couronné
Author-email: couronne.david@gmail.com
Requires-Python: >=3.12,<4.0
Classifier: License :: OSI Approved :: MIT License
Classifier: Programming Language :: Python :: 3
Classifier: Programming Language :: Python :: 3.12
Requires-Dist: markdown (>=3.4.3,<4.0.0)
Requires-Dist: nbconvert (>=7.2.10,<8.0.0)
Requires-Dist: panflute (>=2.3.0,<3.0.0)
Requires-Dist: pillow (>=11.1.0,<12.0.0)
Requires-Dist: python-slugify (>=8.0.1,<9.0.0)
Requires-Dist: requests (>=2.28.2,<3.0.0)
Project-URL: Repository, https://github.com/infocornouaille/jupytercor
